CelPy.py
CelPy-0.0.1.dist-info/LICENSE.txt
CelPy-0.0.1.dist-info/METADATA
CelPy-0.0.1.dist-info/WHEEL
CelPy-0.0.1.dist-info/top_level.txt
CelPy-0.0.1.dist-info/RECORD
