Metadata-Version: 2.1
Name: CelPy
Version: 0.0.1
Summary: A package to solve that some method names are not possible to write for some people
Author: Julius Ay
License: UNKNOWN
Platform: UNKNOWN
Classifier: Programming Language :: Python :: 3
Classifier: License :: Public Domain
Classifier: Operating System :: OS Independent
Requires-Python: >=3.6
License-File: LICENSE.txt
